[
 {
  "quarter": "1912Q2",
  "pdf_page": 464,
  "printed_page": 11,
  "section": "PUNJABI—MISCELLANEOUS—CONCLUDED.",
  "lang": "Punjabi",
  "char": "",
  "topic": "Miscellaneous",
  "serial": 36,
  "reg": "703",
  "copies": "1000",
  "printer_verbatim": "Wazir-i-Hind, Press, Amristsar.",
  "printer": "Wazir-i-Hind, Press",
  "pcity": "Amristsar",
  "author": "Sewaram Singh, Bhai, LL.B.",
  "title": "Qaumi Viddiya Parthaye Lekh",
  "title_native": true,
  "gloss": "A paper on national education among the Sikhs, read before the 5th Sikh Educational Conference.",
  "pp_verbatim": "15",
  "publisher": "The Sikh Educational Committee",
  "pubcity": "Amritsar",
  "date": "1912-04-15",
  "price": "6 pies",
  "edition": "1st",
  "format": "8°",
  "method": "",
  "educ": "",
  "copyright": "",
  "notes": "",
  "marks": "",
  "flags": []
 },
 {
  "quarter": "1912Q2",
  "pdf_page": 464,
  "printed_page": 11,
  "section": "PUNJABI—MISCELLANEOUS—CONCLUDED.",
  "lang": "Punjabi",
  "char": "",
  "topic": "Miscellaneous",
  "serial": 37,
  "reg": "474",
  "copies": "750",
  "printer_verbatim": "Anglo-Urdu-Gur-mukhi Press, Amritsar.",
  "printer": "Anglo-Urdu-Gurmukhi Press",
  "pcity": "Amritsar",
  "author": "Sham Singh, Bhai.",
  "title": "Khalsa Gurmukhi Diary, 1912.",
  "title_native": true,
  "gloss": "",
  "pp_verbatim": "400",
  "publisher": "Author",
  "pubcity": "Amritsar",
  "date": "1912-02-25",
  "price": "8 annas",
  "edition": "1st",
  "format": "16°",
  "method": "",
  "educ": "",
  "copyright": "",
  "notes": "",
  "marks": "",
  "flags": []
 },
 {
  "quarter": "1912Q2",
  "pdf_page": 464,
  "printed_page": 11,
  "section": "PUNJABI—MISCELLANEOUS—CONCLUDED.",
  "lang": "Punjabi",
  "char": "",
  "topic": "Miscellaneous",
  "serial": 38,
  "reg": "594",
  "copies": "1000",
  "printer_verbatim": "Sri Gurmat Press, Amritsar.",
  "printer": "Sri Gurmat Press",
  "pcity": "Amritsar",
  "author": "",
  "title": "Shahr Bengala arthat Bengal de Jadu",
  "title_native": true,
  "gloss": "A book of charms, translated into Punjabi by Bhai Mohan Singh from an Urdu original].",
  "pp_verbatim": "104",
  "publisher": "the translator",
  "pubcity": "Amritsar",
  "date": "1912-04-05",
  "price": "8 annas",
  "edition": "1st",
  "format": "8°",
  "method": "",
  "educ": "",
  "copyright": "",
  "notes": "",
  "marks": "",
  "flags": []
 },
 {
  "quarter": "1912Q2",
  "pdf_page": 464,
  "printed_page": 11,
  "section": "PUNJABI—MISCELLANEOUS—CONCLUDED.",
  "lang": "Punjabi",
  "char": "",
  "topic": "Miscellaneous",
  "serial": 39,
  "reg": "608",
  "copies": "100",
  "printer_verbatim": "Khalsa Press, Ludhiána.",
  "printer": "Khalsa Press",
  "pcity": "Ludhiána",
  "author": "",
  "title": "Ultha Lekha Vibhag Dipka, Riaysat Patiála",
  "title_native": true,
  "gloss": "A translation of the Account Code.]",
  "pp_verbatim": "1 80, 1—74, 1—43, 1—14, 1—6, 1—8, 1—17, 1—51, 1—14, 1—10, 1—22, 1—4, 1—5, 1— 30 and 1- 39",
  "publisher": "the Patiála State",
  "pubcity": "Patiála",
  "date": "1912-04",
  "price": "",
  "edition": "1st",
  "format": "8°",
  "method": "",
  "educ": "",
  "copyright": "",
  "notes": "",
  "marks": "",
  "flags": []
 },
 {
  "quarter": "1912Q2",
  "pdf_page": 464,
  "printed_page": 11,
  "section": "PUNJABI—MISCELLANEOUS—CONCLUDED.",
  "lang": "Punjabi",
  "char": "",
  "topic": "Miscellaneous",
  "serial": 40,
  "reg": "607",
  "copies": "300",
  "printer_verbatim": "Ditto",
  "printer": "Khalsa Press",
  "pcity": "Ludhiána",
  "author": "",
  "title": "Ultha Shankawali",
  "title_native": true,
  "gloss": "A translation of the standard list of objections for audit purposes.]",
  "pp_verbatim": "28",
  "publisher": "the Patiála State",
  "pubcity": "Patiála",
  "date": "1912-04",
  "price": "",
  "edition": "1st",
  "format": "8°",
  "method": "",
  "educ": "",
  "copyright": "",
  "notes": "",
  "marks": "",
  "flags": []
 },
 {
  "quarter": "1912Q2",
  "pdf_page": 464,
  "printed_page": 11,
  "section": "PUNJABI—MISCELLANEOUS—CONCLUDED.",
  "lang": "Punjabi",
  "char": "",
  "topic": "Miscellaneous",
  "serial": 41,
  "reg": "569",
  "copies": "2000",
  "printer_verbatim": "Wazir-i-Hind Press, Amritsar.",
  "printer": "Wazir-i-Hind Press",
  "pcity": "Amritsar",
  "author": "",
  "title": "Uttam Sikhya, Part II",
  "title_native": true,
  "gloss": "On man and his duties to himself and to others. Part II.]",
  "pp_verbatim": "48",
  "publisher": "The Khalsa Tract Society",
  "pubcity": "Amritsar",
  "date": "1912-03-01",
  "price": "9 pies",
  "edition": "1st",
  "format": "16°",
  "method": "",
  "educ": "",
  "copyright": "",
  "notes": "Tract No. 415.",
  "marks": "",
  "flags": []
 },
 {
  "quarter": "1912Q2",
  "pdf_page": 464,
  "printed_page": 11,
  "section": "PUNJABI—MISCELLANEOUS—CONCLUDED.",
  "lang": "Punjabi",
  "char": "",
  "topic": "Miscellaneous",
  "serial": 42,
  "reg": "570",
  "copies": "2000",
  "printer_verbatim": "Ditto",
  "printer": "Wazir-i-Hind Press",
  "pcity": "Amritsar",
  "author": "",
  "title": "Part III",
  "title_native": false,
  "gloss": "",
  "pp_verbatim": "52",
  "publisher": "",
  "pubcity": "",
  "date": "1912-03-01",
  "price": "1 anna",
  "edition": "1st",
  "format": "16°",
  "method": "",
  "educ": "",
  "copyright": "",
  "notes": "",
  "marks": "",
  "flags": []
 },
 {
  "quarter": "1912Q2",
  "pdf_page": 464,
  "printed_page": 11,
  "section": "PUNJABI—MISCELLANEOUS—CONCLUDED.",
  "lang": "Punjabi",
  "char": "",
  "topic": "Miscellaneous",
  "serial": 43,
  "reg": "701",
  "copies": "1000",
  "printer_verbatim": "Ditto",
  "printer": "Wazir-i-Hind Press",
  "pcity": "Amritsar",
  "author": "Vir Singh, Bhai.",
  "title": "Atam Vidaya Parthaye Lekh",
  "title_native": true,
  "gloss": "A paper on religious education among the Sikhs, read before the 5th Sikh Educational Conference.]",
  "pp_verbatim": "36",
  "publisher": "The Sikh Educational Committee",
  "pubcity": "Amritsar",
  "date": "1912-04-15",
  "price": "1 anna, 6 pies",
  "edition": "1st",
  "format": "8°",
  "method": "",
  "educ": "",
  "copyright": "",
  "notes": "",
  "marks": "",
  "flags": []
 },
 {
  "quarter": "1912Q2",
  "pdf_page": 464,
  "printed_page": 11,
  "section": "PUNJABI—MISCELLANEOUS—CONCLUDED.",
  "lang": "Punjabi",
  "char": "",
  "topic": "Miscellaneous",
  "serial": 44,
  "reg": "702",
  "copies": "1000",
  "printer_verbatim": "Ditto",
  "printer": "Wazir-i-Hind Press",
  "pcity": "Amritsar",
  "author": "Vir Singh, Bhai.",
  "title": "Wehre wich Vidiya Parthaye Lekh",
  "title_native": true,
  "gloss": "A paper on the religious and moral education of children by parents. read before the 5th Sikh Educational Conference.]",
  "pp_verbatim": "24",
  "publisher": "The Sikh Educational Committee",
  "pubcity": "Amritsar",
  "date": "1912-04-15",
  "price": "1 anna",
  "edition": "1st",
  "format": "8°",
  "method": "",
  "educ": "",
  "copyright": "",
  "notes": "",
  "marks": "X",
  "flags": []
 }
]