[
 {
  "quarter": "1911Q4",
  "pdf_page": 378,
  "printed_page": 24,
  "section": "URDU—FICTION.",
  "lang": "Urdu",
  "char": "",
  "topic": "Fiction",
  "serial": 34,
  "reg": "1411",
  "copies": "500",
  "printer_verbatim": "Hindustan Steam Press, Lahore.",
  "printer": "Hindustan Steam Press",
  "pcity": "Lahore",
  "author": "Achhar Chand, Thakur",
  "title": "Sanwal Devi",
  "title_native": true,
  "gloss": "A novel describing the story of Sanwal Devi, daughter of Raja Kesari Singh, whose husband died from snake-bite, but was revived by a Sadhu.",
  "pp_verbatim": "64",
  "publisher": "Author",
  "pubcity": "Lahore",
  "date": "1911-09",
  "price": "8 annas",
  "edition": "8th",
  "format": "8°",
  "method": "litho.",
  "educ": "",
  "copyright": "",
  "notes": "[Previous edition noticed in entry No. 2 at page 28 of the Catalogue for the quarter ending the 30th June, 1909.]",
  "marks": "",
  "flags": []
 },
 {
  "quarter": "1911Q4",
  "pdf_page": 378,
  "printed_page": 24,
  "section": "URDU—FICTION.",
  "lang": "Urdu",
  "char": "",
  "topic": "Fiction",
  "serial": 35,
  "reg": "1412",
  "copies": "500",
  "printer_verbatim": "Ditto",
  "printer": "Hindustan Steam Press",
  "pcity": "Lahore",
  "author": "Achhar Chand, Thakur",
  "title": "Rama Bai",
  "title_native": true,
  "gloss": "Story noticed in entry No. 13 at page 28 of the catalogue for the quarter ending the 30th June, 1911.",
  "pp_verbatim": "64",
  "publisher": "Author",
  "pubcity": "Lahore",
  "date": "1911-09",
  "price": "8 annas",
  "edition": "3rd",
  "format": "8°",
  "method": "litho.",
  "educ": "",
  "copyright": "",
  "notes": "",
  "marks": "",
  "flags": []
 },
 {
  "quarter": "1911Q4",
  "pdf_page": 378,
  "printed_page": 24,
  "section": "URDU—FICTION.",
  "lang": "Urdu",
  "char": "",
  "topic": "Fiction",
  "serial": 36,
  "reg": "1413",
  "copies": "500",
  "printer_verbatim": "Ditto",
  "printer": "Hindustan Steam Press",
  "pcity": "Lahore",
  "author": "Achhar Chand, Thakur",
  "title": "Tara Bai",
  "title_native": true,
  "gloss": "Story of Tara Bai, daughter of a Rajput Raja Sheo Ratan of Thoda, who rescued her father's state from the Muhammadans with the help of Prithi Raj, son of Rana Rai Mal of Mewar.",
  "pp_verbatim": "64",
  "publisher": "Author",
  "pubcity": "Lahore",
  "date": "1911-09",
  "price": "8 annas",
  "edition": "5th",
  "format": "8°",
  "method": "litho.",
  "educ": "",
  "copyright": "",
  "notes": "[Previous edition noticed in entry No. 7 at page 25 of the Catalogue for the quarter ending the 30th June, 1909.]",
  "marks": "",
  "flags": []
 },
 {
  "quarter": "1911Q4",
  "pdf_page": 378,
  "printed_page": 24,
  "section": "URDU—FICTION.",
  "lang": "Urdu",
  "char": "",
  "topic": "Fiction",
  "serial": 37,
  "reg": "1414",
  "copies": "500",
  "printer_verbatim": "Ditto",
  "printer": "Hindustan Steam Press",
  "pcity": "Lahore",
  "author": "Achhar Chand, Thakur",
  "title": "Sakuntla",
  "title_native": true,
  "gloss": "A well known story. The plot has been taken from the Sanskrit original by Kali Das.",
  "pp_verbatim": "64",
  "publisher": "Thakur Achhar Chand (compiler)",
  "pubcity": "Lahore",
  "date": "1911-09",
  "price": "8 annas",
  "edition": "2nd",
  "format": "8°",
  "method": "litho.",
  "educ": "",
  "copyright": "",
  "notes": "",
  "marks": "",
  "flags": []
 },
 {
  "quarter": "1911Q4",
  "pdf_page": 378,
  "printed_page": 24,
  "section": "URDU—FICTION.",
  "lang": "Urdu",
  "char": "",
  "topic": "Fiction",
  "serial": 38,
  "reg": "1415",
  "copies": "500",
  "printer_verbatim": "Ditto",
  "printer": "Hindustan Steam Press",
  "pcity": "Lahore",
  "author": "Achhar Chand, Thakur",
  "title": "Darupti",
  "title_native": true,
  "gloss": "A story describing the miseries of a girl written with the object of showing the bad results of an imprudent marriage.",
  "pp_verbatim": "48",
  "publisher": "Author",
  "pubcity": "Lahore",
  "date": "1911-09",
  "price": "6 annas",
  "edition": "9th",
  "format": "8°",
  "method": "litho.",
  "educ": "",
  "copyright": "",
  "notes": "",
  "marks": "",
  "flags": []
 },
 {
  "quarter": "1911Q4",
  "pdf_page": 378,
  "printed_page": 24,
  "section": "URDU—FICTION.",
  "lang": "Urdu",
  "char": "",
  "topic": "Fiction",
  "serial": 39,
  "reg": "1418",
  "copies": "500",
  "printer_verbatim": "Ditto",
  "printer": "Hindustan Steam Press",
  "pcity": "Lahore",
  "author": "Achhar Chand, Thakur",
  "title": "Krishan Kumari",
  "title_native": true,
  "gloss": "Story of Krishan Kumari, daughter of Rana Bhim Singh, of Udepur. The Rajas of Jodhpur and Jaipur fought for her hand, but in order to put an end to further bloodshed she committed suicide.",
  "pp_verbatim": "64",
  "publisher": "Author",
  "pubcity": "Lahore",
  "date": "1911-09",
  "price": "8 annas",
  "edition": "8th",
  "format": "8°",
  "method": "litho.",
  "educ": "",
  "copyright": "",
  "notes": "",
  "marks": "",
  "flags": []
 },
 {
  "quarter": "1911Q4",
  "pdf_page": 378,
  "printed_page": 24,
  "section": "URDU—FICTION.",
  "lang": "Urdu",
  "char": "",
  "topic": "Fiction",
  "serial": 40,
  "reg": "1420",
  "copies": "500",
  "printer_verbatim": "Ditto",
  "printer": "Hindustan Steam Press",
  "pcity": "Lahore",
  "author": "Achhar Chand, Thakur",
  "title": "Durgawati",
  "title_native": true,
  "gloss": "Story of Durgawati, widow of Raja Dilpat, of Garh Mundla, who died while fighting against Akbar's army to save her State.",
  "pp_verbatim": "64",
  "publisher": "Author",
  "pubcity": "Lahore",
  "date": "1911-09",
  "price": "8 annas",
  "edition": "2nd",
  "format": "8°",
  "method": "litho.",
  "educ": "",
  "copyright": "",
  "notes": "",
  "marks": "",
  "flags": []
 },
 {
  "quarter": "1911Q4",
  "pdf_page": 378,
  "printed_page": 24,
  "section": "URDU—FICTION.",
  "lang": "Urdu",
  "char": "",
  "topic": "Fiction",
  "serial": 41,
  "reg": "1419",
  "copies": "500",
  "printer_verbatim": "Ditto",
  "printer": "Hindustan Steam Press",
  "pcity": "Lahore",
  "author": "Achhar Chand, Thakur",
  "title": "Raja Harishchandra",
  "title_native": true,
  "gloss": "Story noticed in entry No. 107, at page 19 of the catalogue for the quarter ending the 30th September, 1908.",
  "pp_verbatim": "64",
  "publisher": "Author",
  "pubcity": "Lahore",
  "date": "1911-09",
  "price": "8 annas",
  "edition": "2nd",
  "format": "8°",
  "method": "litho.",
  "educ": "",
  "copyright": "",
  "notes": "",
  "marks": "",
  "flags": []
 }
]