[
 {
  "quarter": "1911Q2",
  "pdf_page": 293,
  "printed_page": 55,
  "section": "BILINGUAL (ARABIC AND URDU)—RELIGION.",
  "lang": "Bilingual (Arabic and Urdu)",
  "char": "",
  "topic": "Religion",
  "serial": 2,
  "reg": "723",
  "copies": "15,000",
  "printer_verbatim": "Newal Kishore Gas Printing Works, Lahore.",
  "printer": "Newal Kishore Gas Printing Works",
  "pcity": "Lahore",
  "author": "",
  "title": "Dua-i-Ganj-ul-Arsh Mutarjam",
  "title_native": true,
  "gloss": "A Muhammadan prayer with translation into Urdu.",
  "pp_verbatim": "96",
  "publisher": "M. Din Muhammad, Book-seller, Kashmiri Bazar, Lahore",
  "pubcity": "Lahore",
  "date": "1911-01",
  "price": "1 anna 6 pies",
  "edition": "1st",
  "format": "16°",
  "method": "litho.",
  "educ": "",
  "copyright": "",
  "notes": "",
  "marks": "",
  "flags": []
 },
 {
  "quarter": "1911Q2",
  "pdf_page": 293,
  "printed_page": 55,
  "section": "BILINGUAL (ARABIC AND URDU)—RELIGION.",
  "lang": "Bilingual (Arabic and Urdu)",
  "char": "",
  "topic": "Religion",
  "serial": 3,
  "reg": "422",
  "copies": "1,000",
  "printer_verbatim": "Hamidia Steam Press, Lahore.",
  "printer": "Hamidia Steam Press",
  "pcity": "Lahore",
  "author": "",
  "title": "Nur-ut-Tajalli, Tarjama-i-Urdu Munyatul Musalli",
  "title_native": true,
  "gloss": "An Urdu translation of “Munyatul Musalli” A book on Muhammadan prayers and ablutions. The text is in Arabic and its Urdu translation is made by M. Abu Muhammad Ahmad.",
  "pp_verbatim": "184",
  "publisher": "M. Fateh Muhammad, Book-seller, Lahore",
  "pubcity": "Lahore",
  "date": "1911-03-31 (1328 Hijri)",
  "price": "1 Re.",
  "edition": "1st",
  "format": "8°",
  "method": "litho.",
  "educ": "",
  "copyright": "M. Fateh Muhammad, Book-seller, Kashmiri Bazar, Lahore; No. 42, dated the 5th May, 1911.",
  "notes": "",
  "marks": "133",
  "flags": []
 },
 {
  "quarter": "1911Q2",
  "pdf_page": 293,
  "printed_page": 55,
  "section": "BILINGUAL (ARABIC AND URDU)—RELIGION.",
  "lang": "Bilingual (Arabic and Urdu)",
  "char": "",
  "topic": "Religion",
  "serial": 4,
  "reg": "617",
  "copies": "2,000",
  "printer_verbatim": "Civil and Military Organ Press, Ludhiána.",
  "printer": "Civil and Military Organ Press",
  "pcity": "Ludhiána",
  "author": "",
  "title": "Salat-ul-Quran Bi-Ayatil Furqan",
  "title_native": true,
  "gloss": "Certain verses of the Quran with translation in Urdu.",
  "pp_verbatim": "30",
  "publisher": "M. Shah Din, Ludhiána",
  "pubcity": "Ludhiána",
  "date": "1911-03-10",
  "price": "Free",
  "edition": "1st",
  "format": "16°",
  "method": "litho.",
  "educ": "",
  "copyright": "",
  "notes": "",
  "marks": "",
  "flags": []
 },
 {
  "quarter": "1911Q2",
  "pdf_page": 293,
  "printed_page": 55,
  "section": "BILINGUAL (ARABIC AND URDU)—RELIGION.",
  "lang": "Bilingual (Arabic and Urdu)",
  "char": "",
  "topic": "Religion",
  "serial": 5,
  "reg": "421",
  "copies": "500",
  "printer_verbatim": "Hamidia Steam Press, Lahore.",
  "printer": "Hamidia Steam Press",
  "pcity": "Lahore",
  "author": "",
  "title": "Tafsir-ul-Quran, Jild Chaharum",
  "title_native": true,
  "gloss": "Translation and commentary of the six complete Suras of the Quran, viz., ‘Sura Ma‘ida’; ‘An‘am’; ‘Aaraf’; ‘Anfal’; ‘Tauba’; and ‘Yunus’; volume IV.",
  "pp_verbatim": "4.608.",
  "publisher": "Published by the commentator and translator M. Muhammad Insha-ullah, Editor, ‘Watan’, Lahore",
  "pubcity": "Lahore",
  "date": "1911-03-31",
  "price": "3 Rs.",
  "edition": "1st",
  "format": "8°",
  "method": "litho.",
  "educ": "",
  "copyright": "M. Muhammad Insha-ullah, Editor, ‘Watan’, Lahore; No. 41, dated the 5th May, 1911.",
  "notes": "[ Previous volume noticed in entry No. 27, at page 49 of the catalogue for the quarter ending 30th September, 1910. ]",
  "marks": "134",
  "flags": [
   {
    "field": "pp_verbatim",
    "issue": "ambiguous, printed as '4.608.'"
   }
  ]
 },
 {
  "quarter": "1911Q2",
  "pdf_page": 293,
  "printed_page": 55,
  "section": "BILINGUAL (ARABIC AND URDU)—RELIGION.",
  "lang": "Bilingual (Arabic and Urdu)",
  "char": "",
  "topic": "Religion",
  "serial": 6,
  "reg": "416",
  "copies": "500",
  "printer_verbatim": "Islamia Steam Press, Lahore.",
  "printer": "Islamia Steam Press",
  "pcity": "Lahore",
  "author": "",
  "title": "Tarjamat-ul-Quran, Para Tiswan",
  "title_native": true,
  "gloss": "An Urdu translation of the 30th part of the Quran with text in Arabic and commentary in Urdu, from “Surat-i-‘Am” to “Surat-un-Nas”.",
  "pp_verbatim": "4.120.",
  "publisher": "Shaikh Yaqub Ali, Turab, Ahmadi, Editor, ‘Alhakam,’ Qadián",
  "pubcity": "Qadián",
  "date": "1911-03",
  "price": "1 Re.",
  "edition": "1st",
  "format": "4°",
  "method": "litho.",
  "educ": "",
  "copyright": "",
  "notes": "",
  "marks": "135",
  "flags": [
   {
    "field": "pp_verbatim",
    "issue": "ambiguous, printed as '4.120.'"
   }
  ]
 },
 {
  "quarter": "1911Q2",
  "pdf_page": 293,
  "printed_page": 55,
  "section": "BILINGUAL—(ARABIC AND PERSIAN)—RELIGION.",
  "lang": "Bilingual (Arabic and Persian)",
  "char": "",
  "topic": "Religion",
  "serial": 1,
  "reg": "773",
  "copies": "2,100",
  "printer_verbatim": "Newal Kishore Gas Printing Works, Lahore.",
  "printer": "Newal Kishore Gas Printing Works",
  "pcity": "Lahore",
  "author": "",
  "title": "Kanz-ud-daqaiq, Jild-i-Salis",
  "title_native": true,
  "gloss": "or the third volume of the well known book of Fiqah on Muhammadan theology, ritual and law. This part deals with jurisprudence.",
  "pp_verbatim": "232",
  "publisher": "Muhammad Sharif, Book-seller, Peshawar",
  "pubcity": "Peshawar",
  "date": "1911-04 (1329 Hijri)",
  "price": "7 annas",
  "edition": "1st",
  "format": "8°",
  "method": "litho.",
  "educ": "",
  "copyright": "",
  "notes": "",
  "marks": "136",
  "flags": []
 },
 {
  "quarter": "1911Q2",
  "pdf_page": 293,
  "printed_page": 55,
  "section": "BILINGUAL—(ARABIC AND PERSIAN)—RELIGION.",
  "lang": "Bilingual (Arabic and Persian)",
  "char": "",
  "topic": "Religion",
  "serial": 2,
  "reg": "774",
  "copies": "2,100",
  "printer_verbatim": "Ditto",
  "printer": "Newal Kishore Gas Printing Works",
  "pcity": "Lahore",
  "author": "",
  "title": "Part IV.",
  "title_native": true,
  "gloss": "",
  "pp_verbatim": "248",
  "publisher": "Muhammad Sharif, Book-seller, Peshawar",
  "pubcity": "Peshawar",
  "date": "1911-04 (1328 Hijri)",
  "price": "8 annas",
  "edition": "1st",
  "format": "8°",
  "method": "litho.",
  "educ": "",
  "copyright": "",
  "notes": "",
  "marks": "137",
  "flags": []
 }
]