[
 {
  "quarter": "1911Q3",
  "pdf_page": 317,
  "printed_page": 17,
  "section": "PUNJABI (IN THE PERSIAN CHARACTER) POETRY—continued",
  "lang": "Punjabi",
  "char": "Persian character",
  "topic": "Poetry",
  "serial": 207,
  "reg": "1,085",
  "copies": "3000",
  "printer_verbatim": "Newal Kishore Steam Press, Lahore.",
  "printer": "Newal Kishore Steam Press",
  "pcity": "Lahore",
  "author": "Amir Bakhsh, M.",
  "title": "Jang Namah-i-Zaitun, Kalan",
  "title_native": true,
  "gloss": "A description of the battle between Imam Hanif and princess Zaitun, in which the former was victorious and subsequently married the latter].",
  "pp_verbatim": "88",
  "publisher": "Jot Singh Sant Singh, Booksellers, Lahore.",
  "pubcity": "Lahore",
  "date": "1911-06",
  "price": "Price, 2 annas,",
  "edition": "",
  "format": "8°",
  "method": "Litho.",
  "educ": "",
  "copyright": "R",
  "notes": "",
  "marks": "X",
  "flags": []
 },
 {
  "quarter": "1911Q3",
  "pdf_page": 317,
  "printed_page": 17,
  "section": "PUNJABI (IN THE PERSIAN CHARACTER) POETRY—continued",
  "lang": "Punjabi",
  "char": "Persian character",
  "topic": "Poetry",
  "serial": 208,
  "reg": "1,180",
  "copies": "275",
  "printer_verbatim": "Riyaz-i-Hind Press, Amritsar.",
  "printer": "Riyaz-i-Hind Press",
  "pcity": "Amritsar",
  "author": "Arjan Singh, Bh. Bawa.",
  "title": "Gurparkash",
  "title_native": true,
  "gloss": "Biography of the ten Gurus with a brief account of the Rajas of Patiála and Kapúrthala]",
  "pp_verbatim": "48",
  "publisher": "Author",
  "pubcity": "Gurdáspur",
  "date": "1911-08-10",
  "price": "Price, 8 annas.",
  "edition": "1st edition",
  "format": "4°",
  "method": "litho.",
  "educ": "",
  "copyright": "",
  "notes": "",
  "marks": "X",
  "flags": []
 },
 {
  "quarter": "1911Q3",
  "pdf_page": 317,
  "printed_page": 17,
  "section": "PUNJABI (IN THE PERSIAN CHARACTER) POETRY—continued",
  "lang": "Punjabi",
  "char": "Persian character",
  "topic": "Poetry",
  "serial": 209,
  "reg": "992",
  "copies": "2200",
  "printer_verbatim": "Arorbans Press, Amritsar.",
  "printer": "Arorbans Press",
  "pcity": "Amritsar",
  "author": "Arjan Singh, B.",
  "title": "Qissa Bunde Nama",
  "title_native": true,
  "gloss": "Verses describing the ornaments which women generally demand from their husbands.]",
  "pp_verbatim": "8",
  "publisher": "B. Chatar Singh Jiwan Singh, Booksellers, Amritsar.",
  "pubcity": "Amritsar",
  "date": "1911-07-18",
  "price": "Price, 3 pies.",
  "edition": "1st edition",
  "format": "8°",
  "method": "litho.",
  "educ": "",
  "copyright": "",
  "notes": "",
  "marks": "X",
  "flags": []
 },
 {
  "quarter": "1911Q3",
  "pdf_page": 317,
  "printed_page": 17,
  "section": "PUNJABI (IN THE PERSIAN CHARACTER) POETRY—continued",
  "lang": "Punjabi",
  "char": "Persian character",
  "topic": "Poetry",
  "serial": 210,
  "reg": "1170",
  "copies": "1000",
  "printer_verbatim": "Hamidia Steam Press, Lahore.",
  "printer": "Hamidia Steam Press",
  "pcity": "Lahore",
  "author": "Devi Dayal, Pandit.",
  "title": "Puran Bhagat",
  "title_native": true,
  "gloss": "The well-known story of a devout Prince, Puran Bhagat.]",
  "pp_verbatim": "144",
  "publisher": "Bhai Daya Singh, Bookseller, Lahore.",
  "pubcity": "Lahore",
  "date": "1911-07-31",
  "price": "Price, 1 Re.",
  "edition": "1st edition",
  "format": "8°",
  "method": "litho.",
  "educ": "",
  "copyright": "",
  "notes": "",
  "marks": "",
  "flags": []
 },
 {
  "quarter": "1911Q3",
  "pdf_page": 317,
  "printed_page": 17,
  "section": "PUNJABI (IN THE PERSIAN CHARACTER) POETRY—continued",
  "lang": "Punjabi",
  "char": "Persian character",
  "topic": "Poetry",
  "serial": 211,
  "reg": "802",
  "copies": "1000",
  "printer_verbatim": "Hindustan Steam Press, Lahore.",
  "printer": "Hindustan Steam Press",
  "pcity": "Lahore",
  "author": "Ghasita Mal, Chaudhri (nom-de-plume), Ghamnak.",
  "title": "Dil Samundar Dian Lahran",
  "title_native": true,
  "gloss": "Love verses].",
  "pp_verbatim": "32",
  "publisher": "Author",
  "pubcity": "Lahore",
  "date": "1911-06",
  "price": "Price, 4 annas.",
  "edition": "1st edition",
  "format": "4°",
  "method": "litho.",
  "educ": "",
  "copyright": "",
  "notes": "",
  "marks": "",
  "flags": []
 },
 {
  "quarter": "1911Q3",
  "pdf_page": 317,
  "printed_page": 17,
  "section": "PUNJABI (IN THE PERSIAN CHARACTER) POETRY—continued",
  "lang": "Punjabi",
  "char": "Persian character",
  "topic": "Poetry",
  "serial": 212,
  "reg": "1,155",
  "copies": "1000",
  "printer_verbatim": "Hamidia Steam Press, Lahore.",
  "printer": "Hamidia Steam Press",
  "pcity": "Lahore",
  "author": "Ghulam Muhammad, M.",
  "title": "Risala-i-Be Namaz faqiran",
  "title_native": true,
  "gloss": "Advice to the faqirs (beggers) who do not carry out Islamio orders.]",
  "pp_verbatim": "16",
  "publisher": "author",
  "pubcity": "Shahdara Lahore",
  "date": "1911-07-31",
  "price": "Price, 2 annas",
  "edition": "1st edition",
  "format": "8°",
  "method": "litho.",
  "educ": "",
  "copyright": "M. Ghulam Muhammad of Shahdara, Lahore ; No. 138, dated 6th September, 1911,",
  "notes": "",
  "marks": "",
  "flags": [
   {
    "field": "copyright",
    "issue": "date day digit degraded '6th' uncertain"
   }
  ]
 },
 {
  "quarter": "1911Q3",
  "pdf_page": 317,
  "printed_page": 17,
  "section": "PUNJABI (IN THE PERSIAN CHARACTER) POETRY—continued",
  "lang": "Punjabi",
  "char": "Persian character",
  "topic": "Poetry",
  "serial": 213,
  "reg": "942",
  "copies": "2000",
  "printer_verbatim": "Roz Bazar Steam Press, Amritsar.",
  "printer": "Roz Bazar Steam Press",
  "pcity": "Amritsar",
  "author": "Ghulam Mustafa alias Musa.",
  "title": "Faryad-i-Sassi almaruf Dachi Wala Mor Muhar we",
  "title_native": true,
  "gloss": "Subject noticed in entry No. 56 at page 18 of the Catalogue for the quarter ending the 31st March, 1911.]",
  "pp_verbatim": "8",
  "publisher": "Shaikh Abdur Rahman Habib-ur-Rahman, Booksellers, Amritsar.",
  "pubcity": "Amritsar",
  "date": "1911-05-31",
  "price": "Price, 3 pies.",
  "edition": "3rd edition",
  "format": "8°",
  "method": "litho.",
  "educ": "",
  "copyright": "",
  "notes": "[Previous edition noticed in entry No. 57 at page 18 of the Catalogue for the quarter ending the 31st March, 1911.]",
  "marks": "X",
  "flags": []
 },
 {
  "quarter": "1911Q3",
  "pdf_page": 317,
  "printed_page": 17,
  "section": "PUNJABI (IN THE PERSIAN CHARACTER) POETRY—continued",
  "lang": "Punjabi",
  "char": "Persian character",
  "topic": "Poetry",
  "serial": 214,
  "reg": "1156",
  "copies": "1000",
  "printer_verbatim": "Hamidia Steam Press, Lahore.",
  "printer": "Hamidia Steam Press",
  "pcity": "Lahore",
  "author": "Ghulam Rasul, Maulvi.",
  "title": "Dastan Sahib Qiran Hazrat Amir Hamzah, Hissa-i-Siwum",
  "title_native": true,
  "gloss": "Stories relating to Amir Hamza, uncle of Muhammad.]",
  "pp_verbatim": "296",
  "publisher": "Sheikh Umar-ud-din, Bookseller, Kapúrthala State,",
  "pubcity": "Kapúrthala State",
  "date": "1911-07-31",
  "price": "Price, 1 Re.",
  "edition": "1st edition",
  "format": "8°",
  "method": "litho.",
  "educ": "",
  "copyright": "Sheikh Umar-ud-din, Bookseller, Kapurthala; No. 139, dated 5th September, 1911.",
  "notes": "",
  "marks": "",
  "flags": [
   {
    "field": "serial",
    "issue": "handwritten annotation in margin near serial"
   }
  ]
 }
]